setup.cfg
setup.py
buildfox/__init__.py
buildfox.egg-info/PKG-INFO
buildfox.egg-info/SOURCES.txt
buildfox.egg-info/dependency_links.txt
buildfox.egg-info/entry_points.txt
buildfox.egg-info/top_level.txt
buildfox.egg-info/zip-safe