Metadata-Version: 1.1
Name: buildfox
Version: 0.2.1
Summary: Minimalistic ninja generator
Home-page: https://github.com/beardsvibe/buildfox
Author: @beardsvibe
Author-email: info@beardsvibe.com
License: https://github.com/beardsvibe/buildfox/blob/master/license
Keywords: buildfox bf ninja build tool c cpp
Platform: UNKNOWN
Classifier: Development Status :: 3 - Alpha
Classifier: Environment :: Console
Classifier: Intended Audience :: Developers
Classifier: Programming Language :: Python
Classifier: Programming Language :: Python :: 2.7
Classifier: Programming Language :: Python :: 3
Classifier: Programming Language :: Python :: 3.2
Classifier: Programming Language :: Python :: 3.3
Classifier: Programming Language :: Python :: 3.4
Classifier: Programming Language :: Python :: 3.5
Classifier: License :: OSI Approved :: MIT License
Classifier: Topic :: Software Development :: Build Tools
